udata_piwik/__init__.py
udata_piwik/client.py
udata_piwik/factories.py
udata_piwik/models.py
udata_piwik/settings.py
udata_piwik/tasks.py
udata_piwik/views.py
udata_piwik/migrations/2015-10-01-fix-resources-metrics.js
udata_piwik/templates/piwik.html
udata_piwik-4.1.1.dist-info/METADATA
udata_piwik-4.1.1.dist-info/WHEEL
udata_piwik-4.1.1.dist-info/entry_points.txt
udata_piwik-4.1.1.dist-info/top_level.txt
udata_piwik-4.1.1.dist-info/RECORD
