Metadata-Version: 2.1
Name: udata-piwik
Version: 4.1.1
Summary: Piwik/Matomo support for uData
Home-page: https://github.com/opendatateam/udata-piwik
Author: OpenDataTeam
Author-email: contact@opendata.team
License: LGPL
Keywords: udata piwik
Classifier: Development Status :: 3 - Alpha
Classifier: Programming Language :: Python
Classifier: Environment :: Web Environment
Classifier: Operating System :: OS Independent
Classifier: Intended Audience :: Developers
Classifier: Topic :: System :: Software Distribution
Classifier: Programming Language :: Python
Classifier: Programming Language :: Python :: 3
Classifier: Programming Language :: Python :: 3.7
Classifier: Topic :: Software Development :: Libraries :: Python Modules
Requires-Python: >=3.7
Requires-Dist: udata >=3.2.0
Requires-Dist: udata-front >=1.0.0
Provides-Extra: test
Requires-Dist: mock ==5.0.1 ; extra == 'test'
Requires-Dist: pytest ==7.3.1 ; extra == 'test'
Requires-Dist: pytest-flask ==1.2.0 ; extra == 'test'
Requires-Dist: pytest-mock ==3.10.0 ; extra == 'test'
Requires-Dist: requests-mock ==1.10.0 ; extra == 'test'
